Metadata-Version: 1.0
Name: ynd-probability
Version: 1.0
Summary: Gaussian and Binomial distributions
Home-page: UNKNOWN
Author: YOUNKAP NINA Duplex
Author-email: nina.younkap@ccaa.pro
License: UNKNOWN
Platform: UNKNOWN
